aws_glove/__init__.py
aws_glove/aws_athena.py
aws_glove/aws_ec2.py
aws_glove/aws_ecs.py
aws_glove/aws_glue.py
aws_glove/aws_lambda.py
aws_glove/aws_s3.py
aws_glove/aws_scheduler.py
aws_glove/aws_ssm.py
tests/__init__.py
tests/test_aws_athena.py
tests/test_aws_glue.py
tests/test_aws_lambda.py
tests/test_aws_s3.py
tests/test_aws_scheduler.py
tests/test_aws_ssm.py
aws_glove-1.0.27.dist-info/LICENSE
aws_glove-1.0.27.dist-info/METADATA
aws_glove-1.0.27.dist-info/WHEEL
aws_glove-1.0.27.dist-info/top_level.txt
aws_glove-1.0.27.dist-info/RECORD
