Metadata-Version: 2.1
Name: aws-glove
Version: 1.0.27
Summary: AWS를 쉽게 사용할 수 있게 도와줍니다.
Home-page: https://github.com/da-huin/aws_glove
Author: JunYeong Park
Author-email: dahuin000@gmail.com
License: MIT
Download-URL: https://github.com/da-huin/simple_utils/archive/master.zip
Platform: UNKNOWN
Classifier: Programming Language :: Python :: 3
Requires-Dist: boto3
Requires-Dist: pyfolder
Requires-Dist: pyzip
Requires-Dist: template-manager
